pyutra/ColorText.py
pyutra/CoolDebugging.py
pyutra/Extras.py
pyutra/JsonConfig.py
pyutra/__init__.py
pyutra/blocksi/__init__.py
pyutra/blocksi/admin_data.py
pyutra/blocksi/policy_data.py
pyutra/blocksi/user_data.py
pyutra/discord/Nukify.py
pyutra/discord/Webhooks.py
pyutra/discord/__init__.py
pyutra/internet/__init__.py
pyutra/internet/ip.py
pyutra/internet/web.py
pyutra/network/Network.py
pyutra/network/__init__.py
pyutra/pastelib/Pastelib.py
pyutra/pastelib/User.py
pyutra/pastelib/__init__.py
pyutra-1.0.5.4.dist-info/LICENSE
pyutra-1.0.5.4.dist-info/METADATA
pyutra-1.0.5.4.dist-info/WHEEL
pyutra-1.0.5.4.dist-info/top_level.txt
pyutra-1.0.5.4.dist-info/RECORD
