Metadata-Version: 2.1
Name: pyutra
Version: 1.0.5.4
Summary: A Python library that tries to be a jack of all trades.
Home-page: https://github.com/thediamondog/pyutra
Author: TheDiamondOG
Author-email: thediamondogness@gmail.com
License-File: LICENSE
Requires-Dist: requests
